[
  [
    {
      "text": "C=CCOC(=O)CC(=O)N(CC)C(=O)c1ccccc1",
      "relations": [],
      "type": "reactants"
    },
    {
      "text": "C=CC[C@@]1(C)OCCN(C(=O)c2ccccc2)C1=O",
      "relations": [],
      "type": "products",
      "relation": [
        "91% yield",
        "99% ee",
        "50\u00b0C"
      ]
    },
    {
      "relations": [
        "12.5 mol%",
        "L(S)-(F3C)3-t-BuPHOX",
        "L"
      ],
      "type": "catalyst",
      "text": "CC(C)(C)[C@H]1COC(c2cc(C(F)(F)F)ccc2P(c2ccc(C(F)(F)F)cc2)c2ccc(C(F)(F)F)cc2)=N1"
    },
    {
      "relations": [
        "5 mol%"
      ],
      "type": "catalyst",
      "text": "O=C(/C=C/c1ccccc1)/C=C/c1ccccc1.O=C(/C=C/c1ccccc1)/C=C/c1ccccc1.O=C(/C=C/c1ccccc1)/C=C/c1ccccc1.[Pd].[Pd]"
    }
  ],
  [
    {
      "text": "C=CCOC(=O)CC(=O)N(CC)C(=O)c1ccccc1",
      "relations": [],
      "type": "reactants"
    },
    {
      "text": "C=CC[C@@]1(COCc2ccccc2)OCCN(C(=O)c2ccccc2)C1=O",
      "relations": [],
      "type": "products",
      "relation": [
        "80% yield",
        "99% ee",
        "50\u00b0C"
      ]
    },
    {
      "relations": [
        "12.5 mol%",
        "L(S)-(F3C)3-t-BuPHOX",
        "L"
      ],
      "type": "catalyst",
      "text": "CC(C)(C)[C@H]1COC(c2cc(C(F)(F)F)ccc2P(c2ccc(C(F)(F)F)cc2)c2ccc(C(F)(F)F)cc2)=N1"
    },
    {
      "relations": [
        "5 mol%"
      ],
      "type": "catalyst",
      "text": "O=C(/C=C/c1ccccc1)/C=C/c1ccccc1.O=C(/C=C/c1ccccc1)/C=C/c1ccccc1.O=C(/C=C/c1ccccc1)/C=C/c1ccccc1.[Pd].[Pd]"
    }
  ],
  [
    {
      "text": "C=CCOC(=O)CC(=O)N(CC)C(=O)c1ccccc1",
      "relations": [],
      "type": "reactants"
    },
    {
      "text": "C=CC[C@@]1(C)SCCN(C(=O)c2ccccc2)C1=O",
      "relations": [],
      "type": "products",
      "relation": [
        "79% yield",
        "86% ee",
        "50\u00b0C"
      ]
    },
    {
      "relations": [
        "12.5 mol%",
        "L(S)-(F3C)3-t-BuPHOX",
        "L"
      ],
      "type": "catalyst",
      "text": "CC(C)(C)[C@H]1COC(c2cc(C(F)(F)F)ccc2P(c2ccc(C(F)(F)F)cc2)c2ccc(C(F)(F)F)cc2)=N1"
    },
    {
      "relations": [
        "5 mol%"
      ],
      "type": "catalyst",
      "text": "O=C(/C=C/c1ccccc1)/C=C/c1ccccc1.O=C(/C=C/c1ccccc1)/C=C/c1ccccc1.O=C(/C=C/c1ccccc1)/C=C/c1ccccc1.[Pd].[Pd]"
    }
  ],
  [
    {
      "text": "CCOC(=O)C(C)(C)C=O",
      "relations": [],
      "type": "reactants"
    },
    {
      "text": "C=CC[C@@]1(C)OCCN(C(=O)c2ccccc2)C1=O",
      "relations": [],
      "type": "products",
      "relation": [
        "91% yield",
        "99% ee",
        "50\u00b0C"
      ]
    },
    {
      "relations": [
        "12.5 mol%",
        "L(S)-(F3C)3-t-BuPHOX",
        "L"
      ],
      "type": "catalyst",
      "text": "CC(C)(C)[C@H]1COC(c2cc(C(F)(F)F)ccc2P(c2ccc(C(F)(F)F)cc2)c2ccc(C(F)(F)F)cc2)=N1"
    },
    {
      "relations": [
        "5 mol%"
      ],
      "type": "catalyst",
      "text": "O=C(/C=C/c1ccccc1)/C=C/c1ccccc1.O=C(/C=C/c1ccccc1)/C=C/c1ccccc1.O=C(/C=C/c1ccccc1)/C=C/c1ccccc1.[Pd].[Pd]"
    }
  ],
  [
    {
      "text": "C=CCOC(=O)C(C)(C)C=O",
      "relations": [],
      "type": "reactants"
    },
    {
      "text": "C=CC[C@@]1(COCc2ccccc2)OCCN(C(=O)c2ccccc2)C1=O",
      "relations": [],
      "type": "products",
      "relation": [
        "80% yield",
        "99% ee",
        "50\u00b0C"
      ]
    },
    {
      "relations": [
        "12.5 mol%",
        "L(S)-(F3C)3-t-BuPHOX",
        "L"
      ],
      "type": "catalyst",
      "text": "CC(C)(C)[C@H]1COC(c2cc(C(F)(F)F)ccc2P(c2ccc(C(F)(F)F)cc2)c2ccc(C(F)(F)F)cc2)=N1"
    },
    {
      "relations": [
        "5 mol%"
      ],
      "type": "catalyst",
      "text": "O=C(/C=C/c1ccccc1)/C=C/c1ccccc1.O=C(/C=C/c1ccccc1)/C=C/c1ccccc1.O=C(/C=C/c1ccccc1)/C=C/c1ccccc1.[Pd].[Pd]"
    }
  ],
  [
    {
      "text": "CCOC(=O)C(C)(C)C=O",
      "relations": [],
      "type": "reactants"
    },
    {
      "text": "C=CC[C@@]1(C)SCCN(C(=O)c2ccccc2)C1=O",
      "relations": [],
      "type": "products",
      "relation": [
        "79% yield",
        "86% ee",
        "50\u00b0C"
      ]
    },
    {
      "relations": [
        "12.5 mol%",
        "L(S)-(F3C)3-t-BuPHOX",
        "L"
      ],
      "type": "catalyst",
      "text": "CC(C)(C)[C@H]1COC(c2cc(C(F)(F)F)ccc2P(c2ccc(C(F)(F)F)cc2)c2ccc(C(F)(F)F)cc2)=N1"
    },
    {
      "relations": [
        "5 mol%"
      ],
      "type": "catalyst",
      "text": "O=C(/C=C/c1ccccc1)/C=C/c1ccccc1.O=C(/C=C/c1ccccc1)/C=C/c1ccccc1.O=C(/C=C/c1ccccc1)/C=C/c1ccccc1.[Pd].[Pd]"
    }
  ],
  [
    {
      "text": "C=CCOC(=O)C1(C)CON(C(=O)OC(C)(C)C)C1=O",
      "relations": [],
      "type": "reactants"
    },
    {
      "text": "C=CC[C@@]1(C)CON(C(=O)OC(C)(C)C)C1=O",
      "relations": [],
      "type": "products",
      "relation": [
        "95% yield",
        "72% ee",
        "60\u00b0C"
      ]
    },
    {
      "relations": [
        "12.5 mol%",
        "L(S)-(F3C)3-t-BuPHOX",
        "L"
      ],
      "type": "catalyst",
      "text": "CC(C)(C)[C@H]1COC(c2cc(C(F)(F)F)ccc2P(c2ccc(C(F)(F)F)cc2)c2ccc(C(F)(F)F)cc2)=N1"
    },
    {
      "relations": [
        "5 mol%"
      ],
      "type": "catalyst",
      "text": "O=C(/C=C/c1ccccc1)/C=C/c1ccccc1.O=C(/C=C/c1ccccc1)/C=C/c1ccccc1.O=C(/C=C/c1ccccc1)/C=C/c1ccccc1.[Pd].[Pd]"
    }
  ]
]