[
  [
    {
      "text": "O=Cc1ccccc1",
      "relations": [],
      "type": "reactants"
    },
    {
      "text": "C#CC[C@H](O)c1ccccc1",
      "relations": [],
      "type": "products",
      "relation": [
        "75% yield",
        "91% ee"
      ]
    },
    {
      "relations": [
        "1.5 equiv"
      ],
      "text": "C#CCBr",
      "type": "reactants"
    },
    {
      "relations": [],
      "text": "[Cr]",
      "type": "catalyst"
    },
    {
      "relations": [
        "3 mol%",
        "chromium catalyst"
      ],
      "text": "[Cr]",
      "type": "catalyst"
    },
    {
      "relations": [
        "1 mol%",
        "cobalt co-catalyst",
        "Ar = 4-MeOC6H4"
      ],
      "text": "[Co]",
      "type": "catalyst"
    },
    {
      "relations": [],
      "text": "[Mn]",
      "type": "catalyst"
    },
    {
      "relations": [],
      "text": "CC[Si](Cl)(CC)CC",
      "type": "catalyst"
    },
    {
      "relations": [],
      "text": "C1CCOC1",
      "type": "catalyst"
    },
    {
      "relations": [],
      "text": "rt",
      "type": "temperature"
    },
    {
      "relations": [],
      "text": "CC(C)(C)c1ccc2ccc(-c3ccc4c(c3)CCCC4)nc2c1O[Si](O)(Cl)Oc1c(C(C)(C)C)ccc2ccc(-c3ccc4c(c3)CCCC4)nc12",
      "type": "catalyst"
    }
  ],
  [
    {
      "text": "O=CC=Cc1ccccc1",
      "relations": [],
      "type": "reactants"
    },
    {
      "text": "C#CC[C@H](O)C=Cc1ccccc1",
      "relations": [],
      "type": "products",
      "relation": [
        "40% yield",
        "92% ee"
      ]
    },
    {
      "relations": [
        "1.5 equiv"
      ],
      "text": "C#CCBr",
      "type": "reactants"
    },
    {
      "relations": [],
      "text": "[Cr]",
      "type": "catalyst"
    },
    {
      "relations": [
        "3 mol%",
        "chromium catalyst"
      ],
      "text": "[Cr]",
      "type": "catalyst"
    },
    {
      "relations": [
        "1 mol%",
        "cobalt co-catalyst",
        "Ar = 4-MeOC6H4"
      ],
      "text": "[Co]",
      "type": "catalyst"
    },
    {
      "relations": [],
      "text": "[Mn]",
      "type": "catalyst"
    },
    {
      "relations": [],
      "text": "CC[Si](Cl)(CC)CC",
      "type": "catalyst"
    },
    {
      "relations": [],
      "text": "C1CCOC1",
      "type": "catalyst"
    },
    {
      "relations": [],
      "text": "rt",
      "type": "temperature"
    },
    {
      "relations": [],
      "text": "CC(C)(C)c1ccc2ccc(-c3ccc4c(c3)CCCC4)nc2c1O[Si](O)(Cl)Oc1c(C(C)(C)C)ccc2ccc(-c3ccc4c(c3)CCCC4)nc12",
      "type": "catalyst"
    }
  ],
  [
    {
      "text": "O=Cc1cccs1",
      "relations": [],
      "type": "reactants"
    },
    {
      "text": "C#CC[C@H](O)c1cccs1",
      "relations": [],
      "type": "products",
      "relation": [
        "74% yield",
        "80% ee"
      ]
    },
    {
      "relations": [
        "1.5 equiv"
      ],
      "text": "C#CCBr",
      "type": "reactants"
    },
    {
      "relations": [],
      "text": "[Cr]",
      "type": "catalyst"
    },
    {
      "relations": [
        "3 mol%",
        "chromium catalyst"
      ],
      "text": "[Cr]",
      "type": "catalyst"
    },
    {
      "relations": [
        "1 mol%",
        "cobalt co-catalyst",
        "Ar = 4-MeOC6H4"
      ],
      "text": "[Co]",
      "type": "catalyst"
    },
    {
      "relations": [],
      "text": "[Mn]",
      "type": "catalyst"
    },
    {
      "relations": [],
      "text": "CC[Si](Cl)(CC)CC",
      "type": "catalyst"
    },
    {
      "relations": [],
      "text": "C1CCOC1",
      "type": "catalyst"
    },
    {
      "relations": [],
      "text": "rt",
      "type": "temperature"
    },
    {
      "relations": [],
      "text": "CC(C)(C)c1ccc2ccc(-c3ccc4c(c3)CCCC4)nc2c1O[Si](O)(Cl)Oc1c(C(C)(C)C)ccc2ccc(-c3ccc4c(c3)CCCC4)nc12",
      "type": "catalyst"
    }
  ]
]