[
  [
    {
      "text": "O=[N+]([O-])C=Cc1ccccc1",
      "relations": [],
      "type": "reactants"
    },
    {
      "text": "CC(C)(C)SC1=C[C@@H]([C@H](C[N+](=O)[O-])c2ccccc2)OC1=O",
      "relations": [],
      "type": "products",
      "relation": [
        "76% yield",
        "dr=98:2",
        "er=97:3"
      ]
    },
    {
      "relations": [],
      "text": "CC(C)(C)SC1=CCOC1=O",
      "type": "reactants"
    },
    {
      "relations": [],
      "text": "COc1cc(C(/N=C(/NCc2cc3ccccc3cc2-c2ccccc2)NCc2c(-c3ccccc3)cc3ccccc3c2-c2c3ccccc3cc3ccccc23)c2cc(OC)c(OC)c(OC)c2)cc(OC)c1OC",
      "type": "catalyst"
    },
    {
      "relations": [],
      "text": "C1CCOC1",
      "type": "catalyst"
    },
    {
      "relations": [],
      "text": "-40\u00b0C",
      "type": "temperature"
    }
  ],
  [
    {
      "text": "O=[N+]([O-])C=Cc1cccs1",
      "relations": [],
      "type": "reactants"
    },
    {
      "text": "CC(C)(C)SC1=C[C@@H]([C@H](C[N+](=O)[O-])c2cccs2)OC1=O",
      "relations": [],
      "type": "products",
      "relation": [
        "75% yield",
        "dr=98:2",
        "er=94:6"
      ]
    },
    {
      "relations": [],
      "text": "CC(C)(C)SC1=CCOC1=O",
      "type": "reactants"
    },
    {
      "relations": [],
      "text": "COc1cc(C(/N=C(/NCc2cc3ccccc3cc2-c2ccccc2)NCc2c(-c3ccccc3)cc3ccccc3c2-c2c3ccccc3cc3ccccc23)c2cc(OC)c(OC)c(OC)c2)cc(OC)c1OC",
      "type": "catalyst"
    },
    {
      "relations": [],
      "text": "C1CCOC1",
      "type": "catalyst"
    },
    {
      "relations": [],
      "text": "-40\u00b0C",
      "type": "temperature"
    }
  ]
]