[
  [
    {
      "text": "CC(=O)OC(CCc1ccccc1)=C(CCC1CCCCC1)C(=O)O",
      "relations": [],
      "type": "reactants"
    },
    {
      "text": "CC(=O)O[C@@H](CCc1ccccc1)[C@H](CCC1CCCCC1)C(=O)O",
      "relations": [],
      "type": "products",
      "relation": [
        "82% yield",
        "er = 95:5"
      ]
    },
    {
      "relations": [
        "5 mol%",
        "[Rh(S)-Phanephos(cod)]BF4"
      ],
      "text": "c1ccc(P(c2ccccc2)c2cc3ccc2CCc2ccc(c(P(c4ccccc4)c4ccccc4)c2)CC3)cc1",
      "type": "catalyst"
    },
    {
      "relations": [],
      "text": "CO",
      "type": "catalyst"
    },
    {
      "relations": [
        "5 bar"
      ],
      "text": "H2",
      "type": "other conditions"
    },
    {
      "relations": [],
      "text": "MW",
      "type": "other conditions"
    },
    {
      "relations": [],
      "text": "90\u00b0C",
      "type": "temperature"
    },
    {
      "relations": [],
      "text": "30 min",
      "type": "time"
    }
  ],
  [
    {
      "text": "CC(=O)OC(=C(CCC(C)C)C(=O)O)c1ccccc1",
      "relations": [],
      "type": "reactants"
    },
    {
      "text": "CC(=O)O[C@@H](c1ccccc1)[C@H](CCC(C)C)C(=O)O",
      "relations": [],
      "type": "products",
      "relation": [
        "73% yield",
        "er = 96:4"
      ]
    },
    {
      "relations": [
        "5 mol%",
        "[Rh(S)-Phanephos(cod)]BF4"
      ],
      "text": "c1ccc(P(c2ccccc2)c2cc3ccc2CCc2ccc(c(P(c4ccccc4)c4ccccc4)c2)CC3)cc1",
      "type": "catalyst"
    },
    {
      "relations": [],
      "text": "CO",
      "type": "catalyst"
    },
    {
      "relations": [
        "5 bar"
      ],
      "text": "H2",
      "type": "other conditions"
    },
    {
      "relations": [],
      "text": "MW",
      "type": "other conditions"
    },
    {
      "relations": [],
      "text": "90\u00b0C",
      "type": "temperature"
    },
    {
      "relations": [],
      "text": "30 min",
      "type": "time"
    }
  ],
  [
    {
      "text": "CCCCCCCCCCC(C(=O)O)=C(CCc1ccccc1)OC(C)=O",
      "relations": [],
      "type": "reactants"
    },
    {
      "text": "CCCCCCCCCC[C@@H](C(=O)O)[C@H](CCc1ccccc1)OC(C)=O",
      "relations": [],
      "type": "products",
      "relation": [
        "76% yield",
        "er = 96:4"
      ]
    },
    {
      "relations": [
        "5 mol%",
        "[Rh(S)-Phanephos(cod)]BF4"
      ],
      "text": "c1ccc(P(c2ccccc2)c2cc3ccc2CCc2ccc(c(P(c4ccccc4)c4ccccc4)c2)CC3)cc1",
      "type": "catalyst"
    },
    {
      "relations": [],
      "text": "CO",
      "type": "catalyst"
    },
    {
      "relations": [
        "5 bar"
      ],
      "text": "H2",
      "type": "other conditions"
    },
    {
      "relations": [],
      "text": "MW",
      "type": "other conditions"
    },
    {
      "relations": [],
      "text": "90\u00b0C",
      "type": "temperature"
    },
    {
      "relations": [],
      "text": "30 min",
      "type": "time"
    }
  ],
  [
    {
      "text": "CC(=O)OC(COc1ccccc1)=C(CCC1CCCCC1)C(=O)O",
      "relations": [],
      "type": "reactants"
    },
    {
      "text": "CC(=O)O[C@@H](COc1ccccc1)[C@H](CCC1CCCCC1)C(=O)O",
      "relations": [],
      "type": "products",
      "relation": [
        "79% yield",
        "er = 99:1"
      ]
    },
    {
      "relations": [
        "5 mol%",
        "[Rh(S)-Phanephos(cod)]BF4"
      ],
      "text": "c1ccc(P(c2ccccc2)c2cc3ccc2CCc2ccc(c(P(c4ccccc4)c4ccccc4)c2)CC3)cc1",
      "type": "catalyst"
    },
    {
      "relations": [],
      "text": "CO",
      "type": "catalyst"
    },
    {
      "relations": [
        "5 bar"
      ],
      "text": "H2",
      "type": "other conditions"
    },
    {
      "relations": [],
      "text": "MW",
      "type": "other conditions"
    },
    {
      "relations": [],
      "text": "90\u00b0C",
      "type": "temperature"
    },
    {
      "relations": [],
      "text": "30 min",
      "type": "time"
    }
  ],
  [
    {
      "text": "CC(=O)OC(COc1ccccc1)=C(CCC(C)C)C(=O)O",
      "relations": [],
      "type": "reactants"
    },
    {
      "text": "CC(=O)O[C@@H](COc1ccccc1)[C@H](CCC(C)C)C(=O)O",
      "relations": [],
      "type": "products",
      "relation": [
        "86% yield",
        "er = 98:2"
      ]
    },
    {
      "relations": [
        "5 mol%",
        "[Rh(S)-Phanephos(cod)]BF4"
      ],
      "text": "c1ccc(P(c2ccccc2)c2cc3ccc2CCc2ccc(c(P(c4ccccc4)c4ccccc4)c2)CC3)cc1",
      "type": "catalyst"
    },
    {
      "relations": [],
      "text": "CO",
      "type": "catalyst"
    },
    {
      "relations": [
        "5 bar"
      ],
      "text": "H2",
      "type": "other conditions"
    },
    {
      "relations": [],
      "text": "MW",
      "type": "other conditions"
    },
    {
      "relations": [],
      "text": "90\u00b0C",
      "type": "temperature"
    },
    {
      "relations": [],
      "text": "30 min",
      "type": "time"
    }
  ]
]