[
  [
    {
      "text": "c1ccc2[nH]cnc2c1",
      "relations": [],
      "type": "reactants"
    },
    {
      "text": "C=C=CC1CCCCC1",
      "relations": [],
      "type": "reactants"
    },
    {
      "text": "C(=CC1CCCCC1)Cn1cnc2ccccc21",
      "relations": [],
      "type": "products",
      "relation": [
        "89% yield",
        "l/b >99:1",
        "E/Z >98:2",
        "Pd-catalyzed linear-selective method"
      ]
    },
    {
      "relations": [
        "5 mol%",
        "dppf"
      ],
      "type": "catalyst",
      "text": "c1ccc(P(c2ccccc2)c2ccccc2)cc1"
    },
    {
      "relations": [
        "2.5 mol%"
      ],
      "type": "catalyst",
      "text": "C=C[CH2-].C=C[CH2-].[Cl-].[Cl-].[Pd+2].[Pd+2]"
    },
    {
      "relations": [],
      "type": "catalyst",
      "text": "C1CCOC1"
    },
    {
      "relations": [],
      "type": "temperature",
      "text": "80\u00b0C"
    },
    {
      "relations": [],
      "type": "time",
      "text": "18 h"
    }
  ],
  [
    {
      "text": "OCc1nc2ccccc2[nH]1",
      "relations": [],
      "type": "reactants"
    },
    {
      "text": "C=C=CC1CCCCC1",
      "relations": [],
      "type": "reactants"
    },
    {
      "text": "OCc1nc2ccccc2n1CC=CC1CCCCC1",
      "relations": [],
      "type": "products",
      "relation": [
        "89% yield",
        "l/b >99:1",
        "E/Z = 90:10",
        "Pd-catalyzed linear-selective method"
      ]
    },
    {
      "relations": [
        "5 mol%",
        "dppf"
      ],
      "type": "catalyst",
      "text": "c1ccc(P(c2ccccc2)c2ccccc2)cc1"
    },
    {
      "relations": [
        "2.5 mol%"
      ],
      "type": "catalyst",
      "text": "C=C[CH2-].C=C[CH2-].[Cl-].[Cl-].[Pd+2].[Pd+2]"
    },
    {
      "relations": [],
      "type": "catalyst",
      "text": "C1CCOC1"
    },
    {
      "relations": [],
      "type": "temperature",
      "text": "80\u00b0C"
    },
    {
      "relations": [],
      "type": "time",
      "text": "18 h"
    }
  ],
  [
    {
      "text": "c1ccc2[nH]cnc2c1",
      "relations": [],
      "type": "reactants"
    },
    {
      "text": "C=C=C",
      "relations": [],
      "type": "reactants"
    },
    {
      "text": "C=C[C@@H](C1CCCCC1)n1cnc2ccccc21",
      "relations": [],
      "type": "products",
      "relation": [
        "72% yield",
        "97% ee",
        "Rh-catalyzed branched-selective method"
      ]
    },
    {
      "relations": [
        "5 mol%",
        "dppf"
      ],
      "type": "catalyst",
      "text": "c1ccc(P(c2ccccc2)c2ccccc2)cc1"
    },
    {
      "relations": [
        "2.5 mol%"
      ],
      "type": "catalyst",
      "text": "C=C[CH2-].C=C[CH2-].[Cl-].[Cl-].[Pd+2].[Pd+2]"
    },
    {
      "relations": [],
      "type": "catalyst",
      "text": "C1CCOC1"
    },
    {
      "relations": [],
      "type": "temperature",
      "text": "80\u00b0C"
    },
    {
      "relations": [],
      "type": "time",
      "text": "18 h"
    }
  ],
  [
    {
      "text": "CSc1nc2ccccc2[nH]1",
      "relations": [],
      "type": "reactants"
    },
    {
      "text": "C=C=C",
      "relations": [],
      "type": "reactants"
    },
    {
      "text": "C=C[C@@H](C1CCCCC1)n1c(SC)nc2ccccc21",
      "relations": [],
      "type": "products",
      "relation": [
        "77% yield",
        "98% ee",
        "Rh-catalyzed branched-selective method"
      ]
    },
    {
      "relations": [
        "5 mol%",
        "dppf"
      ],
      "type": "catalyst",
      "text": "c1ccc(P(c2ccccc2)c2ccccc2)cc1"
    },
    {
      "relations": [
        "2.5 mol%"
      ],
      "type": "catalyst",
      "text": "C=C[CH2-].C=C[CH2-].[Cl-].[Cl-].[Pd+2].[Pd+2]"
    },
    {
      "relations": [],
      "type": "catalyst",
      "text": "C1CCOC1"
    },
    {
      "relations": [],
      "type": "temperature",
      "text": "80\u00b0C"
    },
    {
      "relations": [],
      "type": "time",
      "text": "18 h"
    }
  ]
]