[
  [
    {
      "text": "C=CC1COC(=O)O1",
      "relations": [],
      "type": "reactants"
    },
    {
      "text": "N=C=O",
      "relations": [],
      "type": "reactants"
    },
    {
      "text": "C=C[C@H]1COC(=O)N1c1cccc(C)c1",
      "relations": [],
      "type": "products",
      "relation": [
        "93% yield",
        "84% ee"
      ]
    },
    {
      "relations": [
        "2.5 mol%"
      ],
      "text": "ClC(Cl)Cl.O=C(C=Cc1ccccc1)C=Cc1ccccc1.O=C(C=Cc1ccccc1)C=Cc1ccccc1.O=C(C=Cc1ccccc1)C=Cc1ccccc1.[Pd].[Pd]",
      "type": "catalyst"
    },
    {
      "relations": [
        "5 mol%",
        "(S)-SEGPHOS"
      ],
      "text": "c1ccc(P(c2ccccc2)c2ccc3c(c2-c2c(P(c4ccccc4)c4ccccc4)ccc4c2OCO4)OCO3)cc1",
      "type": "catalyst"
    },
    {
      "relations": [
        "0.2 M"
      ],
      "text": "C1CCOC1",
      "type": "catalyst"
    },
    {
      "relations": [],
      "text": "40\u00b0C",
      "type": "temperature"
    },
    {
      "relations": [],
      "text": "17 h",
      "type": "time"
    }
  ],
  [
    {
      "text": "C=CC1COC(=O)O1",
      "relations": [],
      "type": "reactants"
    },
    {
      "text": "N=C=O",
      "relations": [],
      "type": "reactants"
    },
    {
      "text": "C=C[C@H]1COC(=O)N1C(=O)c1ccccc1",
      "relations": [],
      "type": "products",
      "relation": [
        "94% yield",
        "37% ee"
      ]
    },
    {
      "relations": [
        "2.5 mol%"
      ],
      "text": "ClC(Cl)Cl.O=C(C=Cc1ccccc1)C=Cc1ccccc1.O=C(C=Cc1ccccc1)C=Cc1ccccc1.O=C(C=Cc1ccccc1)C=Cc1ccccc1.[Pd].[Pd]",
      "type": "catalyst"
    },
    {
      "relations": [
        "5 mol%",
        "(S)-SEGPHOS"
      ],
      "text": "c1ccc(P(c2ccccc2)c2ccc3c(c2-c2c(P(c4ccccc4)c4ccccc4)ccc4c2OCO4)OCO3)cc1",
      "type": "catalyst"
    },
    {
      "relations": [
        "0.2 M"
      ],
      "text": "C1CCOC1",
      "type": "catalyst"
    },
    {
      "relations": [],
      "text": "40\u00b0C",
      "type": "temperature"
    },
    {
      "relations": [],
      "text": "17 h",
      "type": "time"
    }
  ],
  [
    {
      "text": "C=CC1COC(=O)O1",
      "relations": [],
      "type": "reactants"
    },
    {
      "text": "N=C=O",
      "relations": [],
      "type": "reactants"
    },
    {
      "text": "C=C[C@H]1COC(=O)N1S(=O)(=O)c1ccc(C)cc1",
      "relations": [],
      "type": "products",
      "relation": [
        "90% yield",
        "40% ee"
      ]
    },
    {
      "relations": [
        "2.5 mol%"
      ],
      "text": "ClC(Cl)Cl.O=C(C=Cc1ccccc1)C=Cc1ccccc1.O=C(C=Cc1ccccc1)C=Cc1ccccc1.O=C(C=Cc1ccccc1)C=Cc1ccccc1.[Pd].[Pd]",
      "type": "catalyst"
    },
    {
      "relations": [
        "5 mol%",
        "(S)-SEGPHOS"
      ],
      "text": "c1ccc(P(c2ccccc2)c2ccc3c(c2-c2c(P(c4ccccc4)c4ccccc4)ccc4c2OCO4)OCO3)cc1",
      "type": "catalyst"
    },
    {
      "relations": [
        "0.2 M"
      ],
      "text": "C1CCOC1",
      "type": "catalyst"
    },
    {
      "relations": [],
      "text": "40\u00b0C",
      "type": "temperature"
    },
    {
      "relations": [],
      "text": "17 h",
      "type": "time"
    }
  ],
  [
    {
      "text": "C=CC1(c2cccc(OC)c2)COC(=O)O1",
      "relations": [],
      "type": "reactants"
    },
    {
      "text": "COc1cccc(N=C=O)c1",
      "relations": [],
      "type": "reactants"
    },
    {
      "text": "C=C[C@@]1(c2cccc(OC)c2)COC(=O)N1c1ccccc1OC",
      "relations": [],
      "type": "products",
      "relation": [
        "87% yield",
        "99% ee"
      ]
    },
    {
      "relations": [
        "2.5 mol%"
      ],
      "text": "ClC(Cl)Cl.O=C(C=Cc1ccccc1)C=Cc1ccccc1.O=C(C=Cc1ccccc1)C=Cc1ccccc1.O=C(C=Cc1ccccc1)C=Cc1ccccc1.[Pd].[Pd]",
      "type": "catalyst"
    },
    {
      "relations": [
        "5 mol%",
        "(S)-SEGPHOS"
      ],
      "text": "c1ccc(P(c2ccccc2)c2ccc3c(c2-c2c(P(c4ccccc4)c4ccccc4)ccc4c2OCO4)OCO3)cc1",
      "type": "catalyst"
    },
    {
      "relations": [
        "0.2 M"
      ],
      "text": "C1CCOC1",
      "type": "catalyst"
    },
    {
      "relations": [],
      "text": "40\u00b0C",
      "type": "temperature"
    },
    {
      "relations": [],
      "text": "17 h",
      "type": "time"
    }
  ],
  [
    {
      "text": "C=CCCC1(C=C)COC(=O)O1",
      "relations": [],
      "type": "reactants"
    },
    {
      "text": "C=CCCN=C=O",
      "relations": [],
      "type": "reactants"
    },
    {
      "text": "C=CCC[C@]1(C=C)COC(=O)N1c1ccccc1OC",
      "relations": [],
      "type": "products",
      "relation": [
        "71% yield",
        "86% ee"
      ]
    },
    {
      "relations": [
        "2.5 mol%"
      ],
      "text": "ClC(Cl)Cl.O=C(C=Cc1ccccc1)C=Cc1ccccc1.O=C(C=Cc1ccccc1)C=Cc1ccccc1.O=C(C=Cc1ccccc1)C=Cc1ccccc1.[Pd].[Pd]",
      "type": "catalyst"
    },
    {
      "relations": [
        "5 mol%",
        "(S)-SEGPHOS"
      ],
      "text": "c1ccc(P(c2ccccc2)c2ccc3c(c2-c2c(P(c4ccccc4)c4ccccc4)ccc4c2OCO4)OCO3)cc1",
      "type": "catalyst"
    },
    {
      "relations": [
        "0.2 M"
      ],
      "text": "C1CCOC1",
      "type": "catalyst"
    },
    {
      "relations": [],
      "text": "40\u00b0C",
      "type": "temperature"
    },
    {
      "relations": [],
      "text": "17 h",
      "type": "time"
    }
  ],
  [
    {
      "text": "C=CC1(c2ccsc2)COC(=O)O1",
      "relations": [],
      "type": "reactants"
    },
    {
      "text": "O=C=Nc1ccsc1",
      "relations": [],
      "type": "reactants"
    },
    {
      "text": "C=C[C@@]1(c2ccsc2)COC(=O)N1c1ccccc1OC",
      "relations": [],
      "type": "products",
      "relation": [
        "86% yield",
        "81% ee"
      ]
    },
    {
      "relations": [
        "2.5 mol%"
      ],
      "text": "ClC(Cl)Cl.O=C(C=Cc1ccccc1)C=Cc1ccccc1.O=C(C=Cc1ccccc1)C=Cc1ccccc1.O=C(C=Cc1ccccc1)C=Cc1ccccc1.[Pd].[Pd]",
      "type": "catalyst"
    },
    {
      "relations": [
        "5 mol%",
        "(S)-SEGPHOS"
      ],
      "text": "c1ccc(P(c2ccccc2)c2ccc3c(c2-c2c(P(c4ccccc4)c4ccccc4)ccc4c2OCO4)OCO3)cc1",
      "type": "catalyst"
    },
    {
      "relations": [
        "0.2 M"
      ],
      "text": "C1CCOC1",
      "type": "catalyst"
    },
    {
      "relations": [],
      "text": "40\u00b0C",
      "type": "temperature"
    },
    {
      "relations": [],
      "text": "17 h",
      "type": "time"
    }
  ]
]