[
  [
    {
      "text": "C[Si](C)(C)C(O)(C#CI)CCc1ccccc1",
      "relations": [],
      "type": "reactants"
    },
    {
      "text": "CCCCN1C(=O)CCC1=O",
      "relations": [],
      "type": "reactants"
    },
    {
      "text": "CCCCC(I)=C(C(=O)CCc1ccccc1)[Si](C)(C)C",
      "relations": [],
      "type": "products",
      "relation": [
        "94% yield"
      ]
    },
    {
      "relations": [],
      "text": "ClCCl",
      "type": "catalyst"
    },
    {
      "relations": [],
      "text": "-78\u00b0C to rt",
      "type": "temperature"
    },
    {
      "relations": [],
      "text": "15 min to 4 h",
      "type": "time"
    }
  ],
  [
    {
      "text": "C[Si](C)(C)C(O)(C#CI)C1CCCCC1",
      "relations": [],
      "type": "reactants"
    },
    {
      "text": "O=C1CCC(=O)N1COC1CCCCO1",
      "relations": [],
      "type": "reactants"
    },
    {
      "text": "C[Si](C)(C)C(C(=O)C1CCCCC1)=C(I)COC1CCCCO1",
      "relations": [],
      "type": "products",
      "relation": [
        "92% yield"
      ]
    },
    {
      "relations": [],
      "text": "ClCCl",
      "type": "catalyst"
    },
    {
      "relations": [],
      "text": "-78\u00b0C to rt",
      "type": "temperature"
    },
    {
      "relations": [],
      "text": "15 min to 4 h",
      "type": "time"
    }
  ],
  [
    {
      "text": "C[Si](C)(Cc1ccccc1)C(O)(C#CCOC1CCCCO1)CCc1ccccc1",
      "relations": [],
      "type": "reactants"
    },
    {
      "text": "O=C1CCC(=O)N1I",
      "relations": [],
      "type": "reactants"
    },
    {
      "text": "C[Si](C)(Cc1ccccc1)C(C(=O)CCc1ccccc1)=C(I)COC1CCCCO1",
      "relations": [],
      "type": "products",
      "relation": [
        "92% yield"
      ]
    },
    {
      "relations": [],
      "text": "ClCCl",
      "type": "catalyst"
    },
    {
      "relations": [],
      "text": "-78\u00b0C to rt",
      "type": "temperature"
    },
    {
      "relations": [],
      "text": "15 min to 4 h",
      "type": "time"
    }
  ],
  [
    {
      "text": "C[Si](C)(C)C(O)(C#CBr)CCc1ccccc1",
      "relations": [],
      "type": "reactants"
    },
    {
      "text": "CC(OCc1ccccc1)N1C(=O)CCC1=O",
      "relations": [],
      "type": "reactants"
    },
    {
      "text": "CC(OCc1ccccc1)C(Br)=C(C(=O)CCc1ccccc1)[Si](C)(C)C",
      "relations": [],
      "type": "products",
      "relation": [
        "89% yield"
      ]
    },
    {
      "relations": [],
      "text": "ClCCl",
      "type": "catalyst"
    },
    {
      "relations": [],
      "text": "-78\u00b0C to rt",
      "type": "temperature"
    },
    {
      "relations": [],
      "text": "15 min to 4 h",
      "type": "time"
    }
  ],
  [
    {
      "text": "C[Si](C)(C)C(O)(C#CBr)CCc1ccccc1",
      "relations": [],
      "type": "reactants"
    },
    {
      "text": "CC(C)(OCc1ccccc1)N1C(=O)CCC1=O",
      "relations": [],
      "type": "reactants"
    },
    {
      "text": "CC(C)(OCc1ccccc1)C(Br)=C(C(=O)CCc1ccccc1)[Si](C)(C)C",
      "relations": [],
      "type": "products",
      "relation": [
        "85% yield"
      ]
    },
    {
      "relations": [],
      "text": "ClCCl",
      "type": "catalyst"
    },
    {
      "relations": [],
      "text": "-78\u00b0C to rt",
      "type": "temperature"
    },
    {
      "relations": [],
      "text": "15 min to 4 h",
      "type": "time"
    }
  ],
  [
    {
      "text": "C[Si](C)(C)C(O)(C#Cc1ccccc1)C1CCCCC1",
      "relations": [],
      "type": "reactants"
    },
    {
      "text": "O=C1CCC(=O)N1Br",
      "relations": [],
      "type": "reactants"
    },
    {
      "text": "C[Si](C)(C)C(C(=O)C1CCCCC1)=C(Br)c1ccccc1",
      "relations": [],
      "type": "products",
      "relation": [
        "94% yield"
      ]
    },
    {
      "relations": [],
      "text": "ClCCl",
      "type": "catalyst"
    },
    {
      "relations": [],
      "text": "-78\u00b0C to rt",
      "type": "temperature"
    },
    {
      "relations": [],
      "text": "15 min to 4 h",
      "type": "time"
    }
  ],
  [
    {
      "text": "CCCCC#CC(O)(CCc1ccccc1)[Si](C)(C)Cc1ccccc1",
      "relations": [],
      "type": "reactants"
    },
    {
      "text": "O=C1CCC(=O)N1Br",
      "relations": [],
      "type": "reactants"
    },
    {
      "text": "CCCCC(Br)=C(C(=O)CCc1ccccc1)[Si](C)(C)Cc1ccccc1",
      "relations": [],
      "type": "products",
      "relation": [
        "92% yield"
      ]
    },
    {
      "relations": [],
      "text": "ClCCl",
      "type": "catalyst"
    },
    {
      "relations": [],
      "text": "-78\u00b0C to rt",
      "type": "temperature"
    },
    {
      "relations": [],
      "text": "15 min to 4 h",
      "type": "time"
    }
  ],
  [
    {
      "text": "C[Si](C)(Cc1ccccc1)C(O)(C#CBr)CCc1ccccc1",
      "relations": [],
      "type": "reactants"
    },
    {
      "text": "O=C1CCC(=O)N1c1ccccc1",
      "relations": [],
      "type": "reactants"
    },
    {
      "text": "C[Si](C)(Cc1ccccc1)C(C(=O)CCc1ccccc1)=C(Br)c1ccccc1",
      "relations": [],
      "type": "products",
      "relation": [
        "80% yield"
      ]
    },
    {
      "relations": [],
      "text": "ClCCl",
      "type": "catalyst"
    },
    {
      "relations": [],
      "text": "-78\u00b0C to rt",
      "type": "temperature"
    },
    {
      "relations": [],
      "text": "15 min to 4 h",
      "type": "time"
    }
  ]
]