[
  [
    {
      "text": "CC(C)C(CC=O)N1C(=O)CCC1=O",
      "relations": [],
      "type": "reactants"
    },
    {
      "text": "C#CCCCCl",
      "relations": [],
      "type": "reactants"
    },
    {
      "text": "CC1=CC2C(C(=O)Oc3ccc4ccccc4c3)=CC1C2C(C)C",
      "relations": [],
      "type": "conditions"
    },
    {
      "text": "c1ccc(P(CP(c2ccccc2)c2ccccc2)c2ccccc2)cc1",
      "relations": [],
      "type": "conditions"
    },
    {
      "text": "COc1ccc([C@@H](CCCCl)CC(=O)C=CC(C)C)cc1",
      "relations": [],
      "type": "products"
    },
    {
      "relations": [
        "3 mol%"
      ],
      "text": "Rh(nbd)zBF4/dppm",
      "type": "conditions"
    },
    {
      "relations": [
        "2.5 mol%"
      ],
      "text": "[Rh(L1)CI]",
      "type": "conditions"
    },
    {
      "relations": [
        "1.0 equiv"
      ],
      "text": "K2CO3",
      "type": "conditions"
    },
    {
      "relations": [
        "1.5 equiv"
      ],
      "text": "ArB(OH)2",
      "type": "conditions"
    },
    {
      "relations": [
        "1.5 equiv"
      ],
      "text": "MCPBA",
      "type": "conditions"
    },
    {
      "relations": [
        "2.5 equiv"
      ],
      "text": "DBU",
      "type": "conditions"
    }
  ],
  [
    {
      "text": "O=CCC(c1ccccc1)N1C(=O)CCC1=O",
      "relations": [],
      "type": "reactants"
    },
    {
      "text": "C#Cc1ccc(OC)cc1",
      "relations": [],
      "type": "reactants"
    },
    {
      "text": "CC1=CC2C(C(=O)Oc3ccc4ccccc4c3)=CC1C2C(C)C",
      "relations": [],
      "type": "conditions"
    },
    {
      "text": "c1ccc(P(CP(c2ccccc2)c2ccccc2)c2ccccc2)cc1",
      "relations": [],
      "type": "conditions"
    },
    {
      "text": "COc1ccc([C@@H](CC(=O)C=Cc2ccccc2)c2ccccc2)cc1",
      "relations": [],
      "type": "products"
    },
    {
      "relations": [
        "3 mol%"
      ],
      "text": "Rh(nbd)zBF4/dppm",
      "type": "conditions"
    },
    {
      "relations": [
        "2.5 mol%"
      ],
      "text": "[Rh(L1)CI]",
      "type": "conditions"
    },
    {
      "relations": [
        "1.0 equiv"
      ],
      "text": "K2CO3",
      "type": "conditions"
    },
    {
      "relations": [
        "1.5 equiv"
      ],
      "text": "ArB(OH)2",
      "type": "conditions"
    },
    {
      "relations": [
        "1.5 equiv"
      ],
      "text": "MCPBA",
      "type": "conditions"
    },
    {
      "relations": [
        "2.5 equiv"
      ],
      "text": "DBU",
      "type": "conditions"
    }
  ],
  [
    {
      "text": "COc1ccccc1C(CC=O)N1C(=O)CCC1=O",
      "relations": [],
      "type": "reactants"
    },
    {
      "text": "C#Cc1ccc(OC)cc1",
      "relations": [],
      "type": "reactants"
    },
    {
      "text": "CC1=CC2C(C(=O)Oc3ccc4ccccc4c3)=CC1C2C(C)C",
      "relations": [],
      "type": "conditions"
    },
    {
      "text": "c1ccc(P(CP(c2ccccc2)c2ccccc2)c2ccccc2)cc1",
      "relations": [],
      "type": "conditions"
    },
    {
      "text": "COc1ccc([C@@H](CC(=O)C=Cc2ccccc2OC)c2ccccc2)cc1",
      "relations": [],
      "type": "products"
    },
    {
      "relations": [
        "3 mol%"
      ],
      "text": "Rh(nbd)zBF4/dppm",
      "type": "conditions"
    },
    {
      "relations": [
        "2.5 mol%"
      ],
      "text": "[Rh(L1)CI]",
      "type": "conditions"
    },
    {
      "relations": [
        "1.0 equiv"
      ],
      "text": "K2CO3",
      "type": "conditions"
    },
    {
      "relations": [
        "1.5 equiv"
      ],
      "text": "ArB(OH)2",
      "type": "conditions"
    },
    {
      "relations": [
        "1.5 equiv"
      ],
      "text": "MCPBA",
      "type": "conditions"
    },
    {
      "relations": [
        "2.5 equiv"
      ],
      "text": "DBU",
      "type": "conditions"
    }
  ]
]