[
  [
    {
      "text": "O=C1Nc2ccccc2C12Cc1ccccc1C2",
      "relations": [],
      "type": "reactants"
    },
    {
      "text": "O=C1Nc2ccccc2[C@@]12Cc1ccccc1C2=O",
      "relations": [],
      "type": "products"
    },
    {
      "relations": [
        "1 mol%"
      ],
      "text": "Ru-catalyst",
      "type": "conditions"
    },
    {
      "relations": [
        "2.2 equiv"
      ],
      "text": "2,6-dichloropyridine N-oxide",
      "type": "conditions"
    },
    {
      "relations": [
        "0.05 M"
      ],
      "text": "CH2Cl2",
      "type": "conditions"
    },
    {
      "relations": [],
      "text": "50\u00b0C",
      "type": "conditions"
    },
    {
      "relations": [],
      "text": "20 h",
      "type": "conditions"
    },
    {
      "relations": [],
      "text": "then Swern or PCC oxidation",
      "type": "conditions"
    }
  ],
  [
    {
      "text": "O=C1Nc2ccccc2C12Cc1ccccc1C2",
      "relations": [],
      "type": "reactants"
    },
    {
      "text": "COc1cc2c(cc1OC)C(=O)[C@@]1(C2)C(=O)Nc2ccccc21",
      "relations": [],
      "type": "products"
    },
    {
      "relations": [
        "1 mol%"
      ],
      "text": "Ru-catalyst",
      "type": "conditions"
    },
    {
      "relations": [
        "2.2 equiv"
      ],
      "text": "2,6-dichloropyridine N-oxide",
      "type": "conditions"
    },
    {
      "relations": [
        "0.05 M"
      ],
      "text": "CH2Cl2",
      "type": "conditions"
    },
    {
      "relations": [],
      "text": "50\u00b0C",
      "type": "conditions"
    },
    {
      "relations": [],
      "text": "20 h",
      "type": "conditions"
    },
    {
      "relations": [],
      "text": "then Swern or PCC oxidation",
      "type": "conditions"
    }
  ],
  [
    {
      "text": "O=C1Nc2ccccc2C12Cc1ccccc1C2",
      "relations": [],
      "type": "reactants"
    },
    {
      "text": "N#Cc1ccc2c(c1)NC(=O)[C@]21Cc2ccccc2C1=O",
      "relations": [],
      "type": "products"
    },
    {
      "relations": [
        "1 mol%"
      ],
      "text": "Ru-catalyst",
      "type": "conditions"
    },
    {
      "relations": [
        "2.2 equiv"
      ],
      "text": "2,6-dichloropyridine N-oxide",
      "type": "conditions"
    },
    {
      "relations": [
        "0.05 M"
      ],
      "text": "CH2Cl2",
      "type": "conditions"
    },
    {
      "relations": [],
      "text": "50\u00b0C",
      "type": "conditions"
    },
    {
      "relations": [],
      "text": "20 h",
      "type": "conditions"
    },
    {
      "relations": [],
      "text": "then Swern or PCC oxidation",
      "type": "conditions"
    }
  ]
]