[
  [
    {
      "text": "CCOC(=O)C=Cc1ccccc1OC(=O)C=Cc1ccccc1",
      "relations": [],
      "type": "reactants"
    },
    {
      "text": "CCOC(=O)C[C@H]1C(=Cc2ccccc2)C(=O)Oc2ccc3ccccc3c21",
      "relations": [],
      "type": "products"
    },
    {
      "text": "COc1cccc(OC)c1-[n+]1cn2c(n1)COC(C)(C)[C@H]2Cc1ccccc1",
      "relations": [],
      "type": "conditions"
    },
    {
      "relations": [
        "10 mol%"
      ],
      "text": "KHMDS",
      "type": "conditions"
    },
    {
      "relations": [],
      "text": "PhMe",
      "type": "conditions"
    },
    {
      "relations": [],
      "text": "120\u00b0C",
      "type": "conditions"
    },
    {
      "relations": [],
      "text": "20 h",
      "type": "conditions"
    }
  ],
  [
    {
      "text": "CCOC(=O)C=Cc1ccccc1OC(=O)C=Cc1ccco1",
      "relations": [],
      "type": "reactants"
    },
    {
      "text": "CCOC(=O)C[C@@H]1C(=Cc2ccco2)C(=O)Oc2ccc3ccccc3c21",
      "relations": [],
      "type": "products"
    },
    {
      "text": "COc1cccc(OC)c1-[n+]1cn2c(n1)COC(C)(C)[C@H]2Cc1ccccc1",
      "relations": [],
      "type": "conditions"
    },
    {
      "relations": [
        "10 mol%"
      ],
      "text": "KHMDS",
      "type": "conditions"
    },
    {
      "relations": [],
      "text": "PhMe",
      "type": "conditions"
    },
    {
      "relations": [],
      "text": "120\u00b0C",
      "type": "conditions"
    },
    {
      "relations": [],
      "text": "20 h",
      "type": "conditions"
    }
  ]
]